{
    "accessPath":  "C:\\DadosVBA\\BDMETALOSA.accdb",
    "geradoEm":  "2026-03-02T09:33:03",
    "producao":  {
                     "total":  351,
                     "arquivo":  ".\\data-import\\import_producao.csv",
                     "minData":  "2025-11-03",
                     "maxData":  "2026-02-26",
                     "totalPecas":  22356
                 },
    "paradas":  {
                    "total":  1286,
                    "arquivo":  ".\\data-import\\import_paradas.csv",
                    "minData":  "2025-11-03",
                    "maxData":  "2026-02-26"
                }
}
